furical/__init__.py
furical/calculator.py
furical-0.1.1.dist-info/LICENSE
furical-0.1.1.dist-info/METADATA
furical-0.1.1.dist-info/WHEEL
furical-0.1.1.dist-info/entry_points.txt
furical-0.1.1.dist-info/top_level.txt
furical-0.1.1.dist-info/RECORD
