Metadata-Version: 2.1
Name: furical
Version: 0.1.1
Summary: A simple calculator package
Author: MD ARIF AZIZ
Author-email: arifaziz0125@gmail.com
Classifier: Programming Language :: Python :: 3
Classifier: License :: OSI Approved :: MIT License
Classifier: Operating System :: OS Independent
Requires-Python: >=3.6
License-File: LICENSE
